pokeman
tests
